pytest_slow_last.py
pytest_slow_last-0.2.1.dist-info/LICENSE
pytest_slow_last-0.2.1.dist-info/METADATA
pytest_slow_last-0.2.1.dist-info/WHEEL
pytest_slow_last-0.2.1.dist-info/entry_points.txt
pytest_slow_last-0.2.1.dist-info/top_level.txt
pytest_slow_last-0.2.1.dist-info/RECORD
