Metadata-Version: 2.1
Name: pytest-slow-last
Version: 0.2.1
Summary: Run tests in order of execution time (faster tests first)
Home-page: https://github.com/david26694/pytest-slow-last
Author: David Masip Bonet
Author-email: david26694@gmail.com
Maintainer: David Masip Bonet
Maintainer-email: david26694@gmail.com
License: MIT
Classifier: Development Status :: 4 - Beta
Classifier: Framework :: Pytest
Classifier: Intended Audience :: Developers
Classifier: Topic :: Software Development :: Testing
Classifier: Programming Language :: Python
Classifier: Programming Language :: Python :: 3
Classifier: Programming Language :: Python :: 3.5
Classifier: Programming Language :: Python :: 3.6
Classifier: Programming Language :: Python :: 3.7
Classifier: Programming Language :: Python :: 3.8
Classifier: Programming Language :: Python :: 3.9
Classifier: Programming Language :: Python :: 3.10
Classifier: Programming Language :: Python :: 3 :: Only
Classifier: Programming Language :: Python :: Implementation :: CPython
Classifier: Programming Language :: Python :: Implementation :: PyPy
Classifier: Operating System :: OS Independent
Classifier: License :: OSI Approved :: MIT License
Requires-Python: >=3.5
License-File: LICENSE
Requires-Dist: pytest>=3.5.0
Provides-Extra: dev
Requires-Dist: black>=19.10b0; extra == "dev"
Requires-Dist: flake8>=3.8.3; extra == "dev"
Requires-Dist: pytest>=3.5.0; extra == "dev"
Requires-Dist: pre-commit>=2.6.0; extra == "dev"
Requires-Dist: ipykernel>=6.15.1; extra == "dev"
Requires-Dist: twine; extra == "dev"
Requires-Dist: mkdocs==1.2.3; extra == "dev"
Requires-Dist: mkdocs-material==8.0.0; extra == "dev"
Requires-Dist: mkdocstrings==0.18.0; extra == "dev"
Requires-Dist: jinja2<3.1.0; extra == "dev"
Provides-Extra: docs
Requires-Dist: mkdocs==1.2.3; extra == "docs"
Requires-Dist: mkdocs-material==8.0.0; extra == "docs"
Requires-Dist: mkdocstrings==0.18.0; extra == "docs"
Requires-Dist: jinja2<3.1.0; extra == "docs"
Provides-Extra: test
Requires-Dist: black>=19.10b0; extra == "test"
Requires-Dist: flake8>=3.8.3; extra == "test"
Requires-Dist: pytest>=3.5.0; extra == "test"
Provides-Extra: util
Requires-Dist: pre-commit>=2.6.0; extra == "util"
Requires-Dist: ipykernel>=6.15.1; extra == "util"
Requires-Dist: twine; extra == "util"
Requires-Dist: pytest>=3.5.0; extra == "util"
